salutake/__init__.py
salutake/config.cpython-310-x86_64-linux-gnu.so
salutake/decorators.py
salutake/idhns.cpython-310-x86_64-linux-gnu.so
salutake/ighns.cpython-310-x86_64-linux-gnu.so
salutake/msg.py
salutake/adhoc/__init__.py
salutake/adhoc/controllers.cpython-310-x86_64-linux-gnu.so
salutake/adhoc/models.cpython-310-x86_64-linux-gnu.so
salutake/match/__init__.py
salutake/match/controllers.cpython-310-x86_64-linux-gnu.so
salutake/match/models.cpython-310-x86_64-linux-gnu.so
salutake/models/__init__.py
salutake/models/db.cpython-310-x86_64-linux-gnu.so
salutake/models/db2.cpython-310-x86_64-linux-gnu.so
salutake/models/gateways.cpython-310-x86_64-linux-gnu.so
salutake/models/links.cpython-310-x86_64-linux-gnu.so
salutake/models/links2.cpython-310-x86_64-linux-gnu.so
salutake/throughput/__init__.py
salutake/throughput/models.cpython-310-x86_64-linux-gnu.so
salutake/throughput/routes.cpython-310-x86_64-linux-gnu.so
salutake/throughput/controllers/ck.cpython-310-x86_64-linux-gnu.so
salutake/throughput/controllers/cl.cpython-310-x86_64-linux-gnu.so
salutake/throughput/controllers/fl.cpython-310-x86_64-linux-gnu.so
salutake-3.4.0.dist-info/METADATA
salutake-3.4.0.dist-info/WHEEL
salutake-3.4.0.dist-info/top_level.txt
salutake-3.4.0.dist-info/RECORD
