Metadata-Version: 2.4
Name: salutake
Version: 3.4.0
Author: Kenny
Requires-Python: >=3.10
Requires-Dist: requests
Requires-Dist: pandas==1.5.3
Requires-Dist: cython
Requires-Dist: modelswrkpi
Requires-Dist: keyrings.google.artifactregistry-auth
